qwertyenv/__init__.py
qwertyenv/action_wrapper_pz.py
qwertyenv/black_jack.py
qwertyenv/collect_coins.py
qwertyenv/collect_coins_game.py
qwertyenv/collect_coins_pz.py
qwertyenv/ensure_valid_action.py
qwertyenv/ensure_valid_action_pz.py
qwertyenv/pz_to_gymnasium_wrappers.py
qwertyenv/tmp.py
qwertyenv/up_down_left_right.py
tests/__init__.py
tests/test_collect_coins.py
tests/test_collect_coins_gym_from_pz.py
tests/test_collect_coins_pz.py
tests/test_gymnasium_conversions.py
tests/test_up_down_left_right.py
qwertyenv-0.1.1.dist-info/METADATA
qwertyenv-0.1.1.dist-info/WHEEL
qwertyenv-0.1.1.dist-info/top_level.txt
qwertyenv-0.1.1.dist-info/zip-safe
qwertyenv-0.1.1.dist-info/RECORD
